{
  "40825_cx43_Z25": [
    {
      "label_name": "gap_junction",
      "bbox_x": 537.5,
      "bbox_y": 530.5,
      "bbox_width": 17.0,
      "bbox_height": 13.0,
      "image_name": "40825_cx43_Z25.png",
      "image_width": 1635,
      "image_height": 1199,
      "score": 0.85400390625
    },
    {
      "label_name": "gap_junction",
      "bbox_x": 1444.0,
      "bbox_y": 964.0,
      "bbox_width": 17.0,
      "bbox_height": 12.0,
      "image_name": "40825_cx43_Z25.png",
      "image_width": 1635,
      "image_height": 1199,
      "score": 0.84521484375
    },
    {
      "label_name": "gap_junction",
      "bbox_x": 1543.0,
      "bbox_y": 779.5,
      "bbox_width": 18.0,
      "bbox_height": 13.0,
      "image_name": "40825_cx43_Z25.png",
      "image_width": 1635,
      "image_height": 1199,
      "score": 0.8427734375
    },
    {
      "label_name": "gap_junction",
      "bbox_x": 1428.0,
      "bbox_y": 939.5,
      "bbox_width": 15.0,
      "bbox_height": 12.0,
      "image_name": "40825_cx43_Z25.png",
      "image_width": 1635,
      "image_height": 1199,
      "score": 0.82958984375
    },
    {
      "label_name": "gap_junction",
      "bbox_x": 95.25,
      "bbox_y": 916.0,
      "bbox_width": 14.75,
      "bbox_height": 12.0,
      "image_name": "40825_cx43_Z25.png",
      "image_width": 1635,
      "image_height": 1199,
      "score": 0.82177734375
    },
    {
      "label_name": "gap_junction",
      "bbox_x": 606.0,
      "bbox_y": 718.5,
      "bbox_width": 15.5,
      "bbox_height": 11.5,
      "image_name": "40825_cx43_Z25.png",
      "image_width": 1635,
      "image_height": 1199,
      "score": 0.8212890625
    },
    {
      "label_name": "gap_junction",
      "bbox_x": 187.0,
      "bbox_y": 403.75,
      "bbox_width": 16.25,
      "bbox_height": 12.75,
      "image_name": "40825_cx43_Z25.png",
      "image_width": 1635,
      "image_height": 1199,
      "score": 0.82080078125
    },
    {
      "label_name": "gap_junction",
      "bbox_x": 1471.0,
      "bbox_y": 770.5,
      "bbox_width": 16.0,
      "bbox_height": 12.0,
      "image_name": "40825_cx43_Z25.png",
      "image_width": 1635,
      "image_height": 1199,
      "score": 0.818359375
    },
    {
      "label_name": "gap_junction",
      "bbox_x": 465.25,
      "bbox_y": 899.0,
      "bbox_width": 16.75,
      "bbox_height": 12.5,
      "image_name": "40825_cx43_Z25.png",
      "image_width": 1635,
      "image_height": 1199,
      "score": 0.81591796875
    },
    {
      "label_name": "gap_junction",
      "bbox_x": 846.5,
      "bbox_y": 682.0,
      "bbox_width": 16.5,
      "bbox_height": 12.5,
      "image_name": "40825_cx43_Z25.png",
      "image_width": 1635,
      "image_height": 1199,
      "score": 0.81298828125
    },
    {
      "label_name": "gap_junction",
      "bbox_x": 407.5,
      "bbox_y": 380.75,
      "bbox_width": 16.0,
      "bbox_height": 12.0,
      "image_name": "40825_cx43_Z25.png",
      "image_width": 1635,
      "image_height": 1199,
      "score": 0.810546875
    },
    {
      "label_name": "gap_junction",
      "bbox_x": 554.0,
      "bbox_y": 815.5,
      "bbox_width": 14.0,
      "bbox_height": 12.0,
      "image_name": "40825_cx43_Z25.png",
      "image_width": 1635,
      "image_height": 1199,
      "score": 0.80029296875
    },
    {
      "label_name": "gap_junction",
      "bbox_x": 950.0,
      "bbox_y": 422.5,
      "bbox_width": 15.5,
      "bbox_height": 11.5,
      "image_name": "40825_cx43_Z25.png",
      "image_width": 1635,
      "image_height": 1199,
      "score": 0.79736328125
    },
    {
      "label_name": "gap_junction",
      "bbox_x": 1205.0,
      "bbox_y": 127.75,
      "bbox_width": 15.0,
      "bbox_height": 10.875,
      "image_name": "40825_cx43_Z25.png",
      "image_width": 1635,
      "image_height": 1199,
      "score": 0.7861328125
    },
    {
      "label_name": "gap_junction",
      "bbox_x": 432.25,
      "bbox_y": 372.25,
      "bbox_width": 14.25,
      "bbox_height": 12.25,
      "image_name": "40825_cx43_Z25.png",
      "image_width": 1635,
      "image_height": 1199,
      "score": 0.78076171875
    },
    {
      "label_name": "gap_junction",
      "bbox_x": 95.125,
      "bbox_y": 92.5625,
      "bbox_width": 14.6875,
      "bbox_height": 11.5625,
      "image_name": "40825_cx43_Z25.png",
      "image_width": 1635,
      "image_height": 1199,
      "score": 0.767578125
    },
    {
      "label_name": "gap_junction",
      "bbox_x": 521.0,
      "bbox_y": 19.0625,
      "bbox_width": 16.0,
      "bbox_height": 13.53125,
      "image_name": "40825_cx43_Z25.png",
      "image_width": 1635,
      "image_height": 1199,
      "score": 0.76611328125
    },
    {
      "label_name": "gap_junction",
      "bbox_x": 985.0,
      "bbox_y": 752.5,
      "bbox_width": 16.0,
      "bbox_height": 13.0,
      "image_name": "40825_cx43_Z25.png",
      "image_width": 1635,
      "image_height": 1199,
      "score": 0.765625
    },
    {
      "label_name": "gap_junction",
      "bbox_x": 211.25,
      "bbox_y": 967.0,
      "bbox_width": 15.5,
      "bbox_height": 11.5,
      "image_name": "40825_cx43_Z25.png",
      "image_width": 1635,
      "image_height": 1199,
      "score": 0.76416015625
    },
    {
      "label_name": "gap_junction",
      "bbox_x": 644.0,
      "bbox_y": 330.0,
      "bbox_width": 14.0,
      "bbox_height": 13.0,
      "image_name": "40825_cx43_Z25.png",
      "image_width": 1635,
      "image_height": 1199,
      "score": 0.75732421875
    },
    {
      "label_name": "gap_junction",
      "bbox_x": 1037.0,
      "bbox_y": 37.59375,
      "bbox_width": 15.0,
      "bbox_height": 12.21875,
      "image_name": "40825_cx43_Z25.png",
      "image_width": 1635,
      "image_height": 1199,
      "score": 0.75634765625
    },
    {
      "label_name": "gap_junction",
      "bbox_x": 1098.0,
      "bbox_y": 490.75,
      "bbox_width": 16.0,
      "bbox_height": 11.5,
      "image_name": "40825_cx43_Z25.png",
      "image_width": 1635,
      "image_height": 1199,
      "score": 0.75439453125
    },
    {
      "label_name": "gap_junction",
      "bbox_x": 1599.0,
      "bbox_y": 1090.0,
      "bbox_width": 16.0,
      "bbox_height": 12.0,
      "image_name": "40825_cx43_Z25.png",
      "image_width": 1635,
      "image_height": 1199,
      "score": 0.75048828125
    },
    {
      "label_name": "gap_junction",
      "bbox_x": 815.0,
      "bbox_y": 809.5,
      "bbox_width": 14.0,
      "bbox_height": 12.0,
      "image_name": "40825_cx43_Z25.png",
      "image_width": 1635,
      "image_height": 1199,
      "score": 0.7490234375
    },
    {
      "label_name": "gap_junction",
      "bbox_x": 1516.0,
      "bbox_y": 482.75,
      "bbox_width": 14.0,
      "bbox_height": 12.5,
      "image_name": "40825_cx43_Z25.png",
      "image_width": 1635,
      "image_height": 1199,
      "score": 0.74755859375
    },
    {
      "label_name": "gap_junction",
      "bbox_x": 1554.0,
      "bbox_y": 1024.0,
      "bbox_width": 13.0,
      "bbox_height": 13.0,
      "image_name": "40825_cx43_Z25.png",
      "image_width": 1635,
      "image_height": 1199,
      "score": 0.7470703125
    },
    {
      "label_name": "gap_junction",
      "bbox_x": 819.0,
      "bbox_y": 818.5,
      "bbox_width": 15.5,
      "bbox_height": 12.0,
      "image_name": "40825_cx43_Z25.png",
      "image_width": 1635,
      "image_height": 1199,
      "score": 0.7333984375
    },
    {
      "label_name": "gap_junction",
      "bbox_x": 1373.0,
      "bbox_y": 117.6875,
      "bbox_width": 16.0,
      "bbox_height": 12.1875,
      "image_name": "40825_cx43_Z25.png",
      "image_width": 1635,
      "image_height": 1199,
      "score": 0.72998046875
    },
    {
      "label_name": "gap_junction",
      "bbox_x": 623.0,
      "bbox_y": 780.5,
      "bbox_width": 13.5,
      "bbox_height": 10.5,
      "image_name": "40825_cx43_Z25.png",
      "image_width": 1635,
      "image_height": 1199,
      "score": 0.70849609375
    },
    {
      "label_name": "gap_junction",
      "bbox_x": 938.0,
      "bbox_y": 603.0,
      "bbox_width": 14.0,
      "bbox_height": 12.0,
      "image_name": "40825_cx43_Z25.png",
      "image_width": 1635,
      "image_height": 1199,
      "score": 0.703125
    },
    {
      "label_name": "gap_junction",
      "bbox_x": 533.5,
      "bbox_y": 629.5,
      "bbox_width": 13.5,
      "bbox_height": 13.0,
      "image_name": "40825_cx43_Z25.png",
      "image_width": 1635,
      "image_height": 1199,
      "score": 0.70068359375
    },
    {
      "label_name": "gap_junction",
      "bbox_x": 256.0,
      "bbox_y": 1044.0,
      "bbox_width": 13.0,
      "bbox_height": 12.0,
      "image_name": "40825_cx43_Z25.png",
      "image_width": 1635,
      "image_height": 1199,
      "score": 0.6884765625
    },
    {
      "label_name": "gap_junction",
      "bbox_x": 821.5,
      "bbox_y": 120.875,
      "bbox_width": 15.0,
      "bbox_height": 11.5,
      "image_name": "40825_cx43_Z25.png",
      "image_width": 1635,
      "image_height": 1199,
      "score": 0.6845703125
    },
    {
      "label_name": "gap_junction",
      "bbox_x": 1375.0,
      "bbox_y": 725.5,
      "bbox_width": 15.0,
      "bbox_height": 12.0,
      "image_name": "40825_cx43_Z25.png",
      "image_width": 1635,
      "image_height": 1199,
      "score": 0.66552734375
    },
    {
      "label_name": "gap_junction",
      "bbox_x": 1477.0,
      "bbox_y": 1052.0,
      "bbox_width": 13.0,
      "bbox_height": 12.0,
      "image_name": "40825_cx43_Z25.png",
      "image_width": 1635,
      "image_height": 1199,
      "score": 0.66162109375
    },
    {
      "label_name": "gap_junction",
      "bbox_x": 589.0,
      "bbox_y": 1070.0,
      "bbox_width": 13.5,
      "bbox_height": 12.0,
      "image_name": "40825_cx43_Z25.png",
      "image_width": 1635,
      "image_height": 1199,
      "score": 0.65380859375
    },
    {
      "label_name": "gap_junction",
      "bbox_x": 414.25,
      "bbox_y": 634.0,
      "bbox_width": 12.75,
      "bbox_height": 12.0,
      "image_name": "40825_cx43_Z25.png",
      "image_width": 1635,
      "image_height": 1199,
      "score": 0.65234375
    },
    {
      "label_name": "gap_junction",
      "bbox_x": 326.5,
      "bbox_y": 822.5,
      "bbox_width": 15.5,
      "bbox_height": 11.0,
      "image_name": "40825_cx43_Z25.png",
      "image_width": 1635,
      "image_height": 1199,
      "score": 0.6474609375
    },
    {
      "label_name": "gap_junction",
      "bbox_x": 413.0,
      "bbox_y": 184.625,
      "bbox_width": 14.25,
      "bbox_height": 12.375,
      "image_name": "40825_cx43_Z25.png",
      "image_width": 1635,
      "image_height": 1199,
      "score": 0.64501953125
    },
    {
      "label_name": "gap_junction",
      "bbox_x": 1312.0,
      "bbox_y": 119.9375,
      "bbox_width": 15.0,
      "bbox_height": 11.6875,
      "image_name": "40825_cx43_Z25.png",
      "image_width": 1635,
      "image_height": 1199,
      "score": 0.64453125
    },
    {
      "label_name": "gap_junction",
      "bbox_x": 1325.0,
      "bbox_y": 139.375,
      "bbox_width": 14.0,
      "bbox_height": 11.625,
      "image_name": "40825_cx43_Z25.png",
      "image_width": 1635,
      "image_height": 1199,
      "score": 0.64208984375
    },
    {
      "label_name": "gap_junction",
      "bbox_x": 55.1875,
      "bbox_y": 1094.0,
      "bbox_width": 16.3125,
      "bbox_height": 13.0,
      "image_name": "40825_cx43_Z25.png",
      "image_width": 1635,
      "image_height": 1199,
      "score": 0.64208984375
    },
    {
      "label_name": "gap_junction",
      "bbox_x": 416.75,
      "bbox_y": 93.3125,
      "bbox_width": 14.75,
      "bbox_height": 11.8125,
      "image_name": "40825_cx43_Z25.png",
      "image_width": 1635,
      "image_height": 1199,
      "score": 0.62353515625
    },
    {
      "label_name": "gap_junction",
      "bbox_x": 961.0,
      "bbox_y": 479.75,
      "bbox_width": 14.5,
      "bbox_height": 12.0,
      "image_name": "40825_cx43_Z25.png",
      "image_width": 1635,
      "image_height": 1199,
      "score": 0.619140625
    },
    {
      "label_name": "gap_junction",
      "bbox_x": 458.75,
      "bbox_y": 1107.0,
      "bbox_width": 16.25,
      "bbox_height": 13.0,
      "image_name": "40825_cx43_Z25.png",
      "image_width": 1635,
      "image_height": 1199,
      "score": 0.61474609375
    },
    {
      "label_name": "gap_junction",
      "bbox_x": 278.0,
      "bbox_y": 343.0,
      "bbox_width": 13.0,
      "bbox_height": 11.0,
      "image_name": "40825_cx43_Z25.png",
      "image_width": 1635,
      "image_height": 1199,
      "score": 0.611328125
    },
    {
      "label_name": "gap_junction",
      "bbox_x": 1122.0,
      "bbox_y": 481.25,
      "bbox_width": 14.0,
      "bbox_height": 11.25,
      "image_name": "40825_cx43_Z25.png",
      "image_width": 1635,
      "image_height": 1199,
      "score": 0.60791015625
    },
    {
      "label_name": "gap_junction",
      "bbox_x": 1566.0,
      "bbox_y": 335.75,
      "bbox_width": 15.0,
      "bbox_height": 10.5,
      "image_name": "40825_cx43_Z25.png",
      "image_width": 1635,
      "image_height": 1199,
      "score": 0.59765625
    },
    {
      "label_name": "gap_junction",
      "bbox_x": 308.5,
      "bbox_y": 215.875,
      "bbox_width": 15.0,
      "bbox_height": 12.0,
      "image_name": "40825_cx43_Z25.png",
      "image_width": 1635,
      "image_height": 1199,
      "score": 0.59033203125
    },
    {
      "label_name": "gap_junction",
      "bbox_x": 81.5,
      "bbox_y": 265.5,
      "bbox_width": 14.5,
      "bbox_height": 11.75,
      "image_name": "40825_cx43_Z25.png",
      "image_width": 1635,
      "image_height": 1199,
      "score": 0.572265625
    },
    {
      "label_name": "gap_junction",
      "bbox_x": 793.5,
      "bbox_y": 926.0,
      "bbox_width": 14.0,
      "bbox_height": 12.0,
      "image_name": "40825_cx43_Z25.png",
      "image_width": 1635,
      "image_height": 1199,
      "score": 0.5634765625
    },
    {
      "label_name": "gap_junction",
      "bbox_x": 1051.0,
      "bbox_y": 745.0,
      "bbox_width": 13.0,
      "bbox_height": 12.0,
      "image_name": "40825_cx43_Z25.png",
      "image_width": 1635,
      "image_height": 1199,
      "score": 0.55712890625
    },
    {
      "label_name": "gap_junction",
      "bbox_x": 1361.0,
      "bbox_y": 56.78125,
      "bbox_width": 14.0,
      "bbox_height": 11.46875,
      "image_name": "40825_cx43_Z25.png",
      "image_width": 1635,
      "image_height": 1199,
      "score": 0.5546875
    },
    {
      "label_name": "gap_junction",
      "bbox_x": 618.5,
      "bbox_y": 846.5,
      "bbox_width": 13.5,
      "bbox_height": 10.5,
      "image_name": "40825_cx43_Z25.png",
      "image_width": 1635,
      "image_height": 1199,
      "score": 0.55029296875
    },
    {
      "label_name": "gap_junction",
      "bbox_x": 1243.0,
      "bbox_y": 812.5,
      "bbox_width": 12.0,
      "bbox_height": 12.0,
      "image_name": "40825_cx43_Z25.png",
      "image_width": 1635,
      "image_height": 1199,
      "score": 0.53955078125
    },
    {
      "label_name": "gap_junction",
      "bbox_x": 1087.0,
      "bbox_y": 525.5,
      "bbox_width": 16.0,
      "bbox_height": 11.5,
      "image_name": "40825_cx43_Z25.png",
      "image_width": 1635,
      "image_height": 1199,
      "score": 0.53076171875
    },
    {
      "label_name": "gap_junction",
      "bbox_x": 1217.0,
      "bbox_y": 555.0,
      "bbox_width": 15.0,
      "bbox_height": 12.5,
      "image_name": "40825_cx43_Z25.png",
      "image_width": 1635,
      "image_height": 1199,
      "score": 0.51220703125
    },
    {
      "label_name": "gap_junction",
      "bbox_x": 1352.0,
      "bbox_y": 1129.0,
      "bbox_width": 14.0,
      "bbox_height": 10.0,
      "image_name": "40825_cx43_Z25.png",
      "image_width": 1635,
      "image_height": 1199,
      "score": 0.51220703125
    },
    {
      "label_name": "gap_junction",
      "bbox_x": 761.0,
      "bbox_y": 603.0,
      "bbox_width": 14.5,
      "bbox_height": 13.0,
      "image_name": "40825_cx43_Z25.png",
      "image_width": 1635,
      "image_height": 1199,
      "score": 0.4921875
    },
    {
      "label_name": "gap_junction",
      "bbox_x": 1479.0,
      "bbox_y": 656.5,
      "bbox_width": 15.0,
      "bbox_height": 13.0,
      "image_name": "40825_cx43_Z25.png",
      "image_width": 1635,
      "image_height": 1199,
      "score": 0.48388671875
    },
    {
      "label_name": "gap_junction",
      "bbox_x": 92.375,
      "bbox_y": 980.5,
      "bbox_width": 13.875,
      "bbox_height": 13.0,
      "image_name": "40825_cx43_Z25.png",
      "image_width": 1635,
      "image_height": 1199,
      "score": 0.48291015625
    },
    {
      "label_name": "gap_junction",
      "bbox_x": 1440.0,
      "bbox_y": 49.34375,
      "bbox_width": 12.0,
      "bbox_height": 11.34375,
      "image_name": "40825_cx43_Z25.png",
      "image_width": 1635,
      "image_height": 1199,
      "score": 0.4775390625
    },
    {
      "label_name": "gap_junction",
      "bbox_x": 778.5,
      "bbox_y": 1175.0,
      "bbox_width": 15.5,
      "bbox_height": 12.0,
      "image_name": "40825_cx43_Z25.png",
      "image_width": 1635,
      "image_height": 1199,
      "score": 0.476318359375
    },
    {
      "label_name": "gap_junction",
      "bbox_x": 1057.0,
      "bbox_y": 1050.0,
      "bbox_width": 13.0,
      "bbox_height": 13.0,
      "image_name": "40825_cx43_Z25.png",
      "image_width": 1635,
      "image_height": 1199,
      "score": 0.47119140625
    },
    {
      "label_name": "gap_junction",
      "bbox_x": 427.25,
      "bbox_y": 521.5,
      "bbox_width": 12.75,
      "bbox_height": 11.5,
      "image_name": "40825_cx43_Z25.png",
      "image_width": 1635,
      "image_height": 1199,
      "score": 0.466552734375
    },
    {
      "label_name": "gap_junction",
      "bbox_x": 931.0,
      "bbox_y": 78.3125,
      "bbox_width": 15.0,
      "bbox_height": 12.0,
      "image_name": "40825_cx43_Z25.png",
      "image_width": 1635,
      "image_height": 1199,
      "score": 0.466552734375
    },
    {
      "label_name": "gap_junction",
      "bbox_x": 1184.0,
      "bbox_y": 302.0,
      "bbox_width": 14.0,
      "bbox_height": 12.0,
      "image_name": "40825_cx43_Z25.png",
      "image_width": 1635,
      "image_height": 1199,
      "score": 0.46240234375
    },
    {
      "label_name": "gap_junction",
      "bbox_x": 780.5,
      "bbox_y": 730.0,
      "bbox_width": 12.0,
      "bbox_height": 11.0,
      "image_name": "40825_cx43_Z25.png",
      "image_width": 1635,
      "image_height": 1199,
      "score": 0.458740234375
    },
    {
      "label_name": "gap_junction",
      "bbox_x": 1149.0,
      "bbox_y": 374.75,
      "bbox_width": 14.0,
      "bbox_height": 11.75,
      "image_name": "40825_cx43_Z25.png",
      "image_width": 1635,
      "image_height": 1199,
      "score": 0.450927734375
    },
    {
      "label_name": "gap_junction",
      "bbox_x": 1189.0,
      "bbox_y": 268.25,
      "bbox_width": 13.0,
      "bbox_height": 10.5,
      "image_name": "40825_cx43_Z25.png",
      "image_width": 1635,
      "image_height": 1199,
      "score": 0.439697265625
    },
    {
      "label_name": "gap_junction",
      "bbox_x": 487.25,
      "bbox_y": 284.0,
      "bbox_width": 13.5,
      "bbox_height": 11.75,
      "image_name": "40825_cx43_Z25.png",
      "image_width": 1635,
      "image_height": 1199,
      "score": 0.43798828125
    },
    {
      "label_name": "gap_junction",
      "bbox_x": 1007.5,
      "bbox_y": 225.5,
      "bbox_width": 13.0,
      "bbox_height": 12.375,
      "image_name": "40825_cx43_Z25.png",
      "image_width": 1635,
      "image_height": 1199,
      "score": 0.43603515625
    },
    {
      "label_name": "gap_junction",
      "bbox_x": 424.25,
      "bbox_y": 1013.0,
      "bbox_width": 14.25,
      "bbox_height": 11.0,
      "image_name": "40825_cx43_Z25.png",
      "image_width": 1635,
      "image_height": 1199,
      "score": 0.42822265625
    },
    {
      "label_name": "gap_junction",
      "bbox_x": 14.7265625,
      "bbox_y": 83.3125,
      "bbox_width": 13.6015625,
      "bbox_height": 11.4375,
      "image_name": "40825_cx43_Z25.png",
      "image_width": 1635,
      "image_height": 1199,
      "score": 0.42724609375
    },
    {
      "label_name": "gap_junction",
      "bbox_x": 758.0,
      "bbox_y": 725.0,
      "bbox_width": 13.5,
      "bbox_height": 13.0,
      "image_name": "40825_cx43_Z25.png",
      "image_width": 1635,
      "image_height": 1199,
      "score": 0.426513671875
    },
    {
      "label_name": "gap_junction",
      "bbox_x": 1062.0,
      "bbox_y": 787.0,
      "bbox_width": 14.0,
      "bbox_height": 13.0,
      "image_name": "40825_cx43_Z25.png",
      "image_width": 1635,
      "image_height": 1199,
      "score": 0.4248046875
    },
    {
      "label_name": "gap_junction",
      "bbox_x": 1245.0,
      "bbox_y": 304.0,
      "bbox_width": 13.0,
      "bbox_height": 11.0,
      "image_name": "40825_cx43_Z25.png",
      "image_width": 1635,
      "image_height": 1199,
      "score": 0.421875
    },
    {
      "label_name": "gap_junction",
      "bbox_x": 959.0,
      "bbox_y": 1134.0,
      "bbox_width": 12.5,
      "bbox_height": 12.0,
      "image_name": "40825_cx43_Z25.png",
      "image_width": 1635,
      "image_height": 1199,
      "score": 0.386962890625
    },
    {
      "label_name": "gap_junction",
      "bbox_x": 1587.0,
      "bbox_y": 838.0,
      "bbox_width": 12.0,
      "bbox_height": 13.0,
      "image_name": "40825_cx43_Z25.png",
      "image_width": 1635,
      "image_height": 1199,
      "score": 0.3759765625
    },
    {
      "label_name": "gap_junction",
      "bbox_x": 1122.0,
      "bbox_y": 928.0,
      "bbox_width": 13.0,
      "bbox_height": 11.5,
      "image_name": "40825_cx43_Z25.png",
      "image_width": 1635,
      "image_height": 1199,
      "score": 0.37353515625
    },
    {
      "label_name": "gap_junction",
      "bbox_x": 292.25,
      "bbox_y": 1151.0,
      "bbox_width": 15.5,
      "bbox_height": 12.0,
      "image_name": "40825_cx43_Z25.png",
      "image_width": 1635,
      "image_height": 1199,
      "score": 0.373046875
    },
    {
      "label_name": "gap_junction",
      "bbox_x": 965.5,
      "bbox_y": 617.5,
      "bbox_width": 14.5,
      "bbox_height": 13.5,
      "image_name": "40825_cx43_Z25.png",
      "image_width": 1635,
      "image_height": 1199,
      "score": 0.370361328125
    },
    {
      "label_name": "gap_junction",
      "bbox_x": 241.375,
      "bbox_y": 1047.0,
      "bbox_width": 15.625,
      "bbox_height": 13.0,
      "image_name": "40825_cx43_Z25.png",
      "image_width": 1635,
      "image_height": 1199,
      "score": 0.36767578125
    },
    {
      "label_name": "gap_junction",
      "bbox_x": 41.9375,
      "bbox_y": 243.875,
      "bbox_width": 14.34375,
      "bbox_height": 12.125,
      "image_name": "40825_cx43_Z25.png",
      "image_width": 1635,
      "image_height": 1199,
      "score": 0.36767578125
    },
    {
      "label_name": "gap_junction",
      "bbox_x": 352.75,
      "bbox_y": 853.0,
      "bbox_width": 14.25,
      "bbox_height": 12.0,
      "image_name": "40825_cx43_Z25.png",
      "image_width": 1635,
      "image_height": 1199,
      "score": 0.366943359375
    },
    {
      "label_name": "gap_junction",
      "bbox_x": 671.5,
      "bbox_y": 744.5,
      "bbox_width": 14.5,
      "bbox_height": 11.5,
      "image_name": "40825_cx43_Z25.png",
      "image_width": 1635,
      "image_height": 1199,
      "score": 0.36376953125
    },
    {
      "label_name": "gap_junction",
      "bbox_x": 180.5,
      "bbox_y": 86.0,
      "bbox_width": 14.125,
      "bbox_height": 12.5625,
      "image_name": "40825_cx43_Z25.png",
      "image_width": 1635,
      "image_height": 1199,
      "score": 0.362060546875
    },
    {
      "label_name": "gap_junction",
      "bbox_x": 270.0,
      "bbox_y": 1088.0,
      "bbox_width": 13.5,
      "bbox_height": 12.0,
      "image_name": "40825_cx43_Z25.png",
      "image_width": 1635,
      "image_height": 1199,
      "score": 0.362060546875
    },
    {
      "label_name": "gap_junction",
      "bbox_x": 205.375,
      "bbox_y": 731.5,
      "bbox_width": 13.0,
      "bbox_height": 12.0,
      "image_name": "40825_cx43_Z25.png",
      "image_width": 1635,
      "image_height": 1199,
      "score": 0.361572265625
    },
    {
      "label_name": "gap_junction",
      "bbox_x": 1342.0,
      "bbox_y": 742.0,
      "bbox_width": 15.0,
      "bbox_height": 12.0,
      "image_name": "40825_cx43_Z25.png",
      "image_width": 1635,
      "image_height": 1199,
      "score": 0.361328125
    },
    {
      "label_name": "gap_junction",
      "bbox_x": 896.0,
      "bbox_y": 505.75,
      "bbox_width": 15.0,
      "bbox_height": 12.25,
      "image_name": "40825_cx43_Z25.png",
      "image_width": 1635,
      "image_height": 1199,
      "score": 0.3515625
    },
    {
      "label_name": "gap_junction",
      "bbox_x": 211.25,
      "bbox_y": 889.0,
      "bbox_width": 13.625,
      "bbox_height": 12.0,
      "image_name": "40825_cx43_Z25.png",
      "image_width": 1635,
      "image_height": 1199,
      "score": 0.35107421875
    },
    {
      "label_name": "gap_junction",
      "bbox_x": 839.0,
      "bbox_y": 456.5,
      "bbox_width": 12.5,
      "bbox_height": 12.5,
      "image_name": "40825_cx43_Z25.png",
      "image_width": 1635,
      "image_height": 1199,
      "score": 0.3505859375
    },
    {
      "label_name": "gap_junction",
      "bbox_x": 270.5,
      "bbox_y": 584.5,
      "bbox_width": 14.25,
      "bbox_height": 12.0,
      "image_name": "40825_cx43_Z25.png",
      "image_width": 1635,
      "image_height": 1199,
      "score": 0.3466796875
    },
    {
      "label_name": "gap_junction",
      "bbox_x": 1224.0,
      "bbox_y": 126.125,
      "bbox_width": 13.0,
      "bbox_height": 12.25,
      "image_name": "40825_cx43_Z25.png",
      "image_width": 1635,
      "image_height": 1199,
      "score": 0.336669921875
    },
    {
      "label_name": "gap_junction",
      "bbox_x": 214.0,
      "bbox_y": 683.0,
      "bbox_width": 15.625,
      "bbox_height": 14.0,
      "image_name": "40825_cx43_Z25.png",
      "image_width": 1635,
      "image_height": 1199,
      "score": 0.324951171875
    },
    {
      "label_name": "gap_junction",
      "bbox_x": 470.0,
      "bbox_y": 664.5,
      "bbox_width": 13.5,
      "bbox_height": 12.0,
      "image_name": "40825_cx43_Z25.png",
      "image_width": 1635,
      "image_height": 1199,
      "score": 0.302490234375
    },
    {
      "label_name": "gap_junction",
      "bbox_x": 452.0,
      "bbox_y": 640.5,
      "bbox_width": 14.25,
      "bbox_height": 13.0,
      "image_name": "40825_cx43_Z25.png",
      "image_width": 1635,
      "image_height": 1199,
      "score": 0.3017578125
    },
    {
      "label_name": "gap_junction",
      "bbox_x": 384.75,
      "bbox_y": 557.0,
      "bbox_width": 13.75,
      "bbox_height": 12.5,
      "image_name": "40825_cx43_Z25.png",
      "image_width": 1635,
      "image_height": 1199,
      "score": 0.294921875
    },
    {
      "label_name": "gap_junction",
      "bbox_x": 639.5,
      "bbox_y": 1003.0,
      "bbox_width": 13.5,
      "bbox_height": 11.5,
      "image_name": "40825_cx43_Z25.png",
      "image_width": 1635,
      "image_height": 1199,
      "score": 0.2939453125
    },
    {
      "label_name": "gap_junction",
      "bbox_x": 509.0,
      "bbox_y": 99.875,
      "bbox_width": 14.5,
      "bbox_height": 12.5625,
      "image_name": "40825_cx43_Z25.png",
      "image_width": 1635,
      "image_height": 1199,
      "score": 0.29150390625
    },
    {
      "label_name": "gap_junction",
      "bbox_x": 155.0,
      "bbox_y": 448.0,
      "bbox_width": 14.125,
      "bbox_height": 13.75,
      "image_name": "40825_cx43_Z25.png",
      "image_width": 1635,
      "image_height": 1199,
      "score": 0.28759765625
    },
    {
      "label_name": "gap_junction",
      "bbox_x": 1345.0,
      "bbox_y": 934.0,
      "bbox_width": 12.0,
      "bbox_height": 12.0,
      "image_name": "40825_cx43_Z25.png",
      "image_width": 1635,
      "image_height": 1199,
      "score": 0.286376953125
    },
    {
      "label_name": "gap_junction",
      "bbox_x": 1259.0,
      "bbox_y": 268.0,
      "bbox_width": 14.0,
      "bbox_height": 12.25,
      "image_name": "40825_cx43_Z25.png",
      "image_width": 1635,
      "image_height": 1199,
      "score": 0.28564453125
    },
    {
      "label_name": "gap_junction",
      "bbox_x": 665.0,
      "bbox_y": 321.5,
      "bbox_width": 14.0,
      "bbox_height": 14.25,
      "image_name": "40825_cx43_Z25.png",
      "image_width": 1635,
      "image_height": 1199,
      "score": 0.284423828125
    },
    {
      "label_name": "gap_junction",
      "bbox_x": 131.875,
      "bbox_y": 945.5,
      "bbox_width": 12.375,
      "bbox_height": 12.5,
      "image_name": "40825_cx43_Z25.png",
      "image_width": 1635,
      "image_height": 1199,
      "score": 0.281494140625
    },
    {
      "label_name": "gap_junction",
      "bbox_x": 1029.0,
      "bbox_y": 730.0,
      "bbox_width": 15.0,
      "bbox_height": 12.5,
      "image_name": "40825_cx43_Z25.png",
      "image_width": 1635,
      "image_height": 1199,
      "score": 0.279052734375
    },
    {
      "label_name": "gap_junction",
      "bbox_x": 65.5,
      "bbox_y": 925.0,
      "bbox_width": 13.9375,
      "bbox_height": 13.5,
      "image_name": "40825_cx43_Z25.png",
      "image_width": 1635,
      "image_height": 1199,
      "score": 0.275146484375
    },
    {
      "label_name": "gap_junction",
      "bbox_x": 629.5,
      "bbox_y": 617.5,
      "bbox_width": 13.0,
      "bbox_height": 13.5,
      "image_name": "40825_cx43_Z25.png",
      "image_width": 1635,
      "image_height": 1199,
      "score": 0.27490234375
    },
    {
      "label_name": "gap_junction",
      "bbox_x": 62.40625,
      "bbox_y": 190.25,
      "bbox_width": 14.40625,
      "bbox_height": 12.5,
      "image_name": "40825_cx43_Z25.png",
      "image_width": 1635,
      "image_height": 1199,
      "score": 0.27294921875
    },
    {
      "label_name": "gap_junction",
      "bbox_x": 1439.0,
      "bbox_y": 328.0,
      "bbox_width": 13.0,
      "bbox_height": 12.25,
      "image_name": "40825_cx43_Z25.png",
      "image_width": 1635,
      "image_height": 1199,
      "score": 0.272216796875
    },
    {
      "label_name": "gap_junction",
      "bbox_x": 1194.0,
      "bbox_y": 644.5,
      "bbox_width": 16.0,
      "bbox_height": 12.0,
      "image_name": "40825_cx43_Z25.png",
      "image_width": 1635,
      "image_height": 1199,
      "score": 0.262939453125
    },
    {
      "label_name": "gap_junction",
      "bbox_x": 1151.0,
      "bbox_y": 402.5,
      "bbox_width": 13.0,
      "bbox_height": 12.5,
      "image_name": "40825_cx43_Z25.png",
      "image_width": 1635,
      "image_height": 1199,
      "score": 0.262939453125
    },
    {
      "label_name": "gap_junction",
      "bbox_x": 836.5,
      "bbox_y": 412.0,
      "bbox_width": 14.5,
      "bbox_height": 13.0,
      "image_name": "40825_cx43_Z25.png",
      "image_width": 1635,
      "image_height": 1199,
      "score": 0.25634765625
    },
    {
      "label_name": "gap_junction",
      "bbox_x": 1372.0,
      "bbox_y": 204.25,
      "bbox_width": 16.0,
      "bbox_height": 14.25,
      "image_name": "40825_cx43_Z25.png",
      "image_width": 1635,
      "image_height": 1199,
      "score": 0.2509765625
    }
  ]
}